bot/__init__.py
bot/config.py
bot/data.json
bot/data_handler.py
bot/embeddings.py
bot/main.py
bot/response_generator.py
bot/semantic_search.py
bot/translator.py
cfcp-0.1.3.dist-info/METADATA
cfcp-0.1.3.dist-info/WHEEL
cfcp-0.1.3.dist-info/entry_points.txt
cfcp-0.1.3.dist-info/top_level.txt
cfcp-0.1.3.dist-info/RECORD
